CHANGES.rst
CONTRIBUTORS.rst
MANIFEST.in
README.rst
constraints.txt
constraints_plone51.txt
constraints_plone52.txt
requirements.1.txt
requirements.txt
setup.cfg
setup.py
docs/LICENSE.GPL
docs/LICENSE.rst
docs/index.rst
src/collective/__init__.py
src/collective.tiles.advancedstatic.egg-info/PKG-INFO
src/collective.tiles.advancedstatic.egg-info/SOURCES.txt
src/collective.tiles.advancedstatic.egg-info/dependency_links.txt
src/collective.tiles.advancedstatic.egg-info/entry_points.txt
src/collective.tiles.advancedstatic.egg-info/namespace_packages.txt
src/collective.tiles.advancedstatic.egg-info/not-zip-safe
src/collective.tiles.advancedstatic.egg-info/requires.txt
src/collective.tiles.advancedstatic.egg-info/top_level.txt
src/collective/tiles/__init__.py
src/collective/tiles/advancedstatic/__init__.py
src/collective/tiles/advancedstatic/configure.zcml
src/collective/tiles/advancedstatic/interfaces.py
src/collective/tiles/advancedstatic/setuphandlers.py
src/collective/tiles/advancedstatic/testing.py
src/collective/tiles/advancedstatic/tile.pt
src/collective/tiles/advancedstatic/tile.py
src/collective/tiles/advancedstatic/vocabulary.py
src/collective/tiles/advancedstatic/locales/collective.tiles.advancedstatic.pot
src/collective/tiles/advancedstatic/locales/update.sh
src/collective/tiles/advancedstatic/locales/it/LC_MESSAGES/collective.tiles.advancedstatic.po
src/collective/tiles/advancedstatic/profiles/default/browserlayer.xml
src/collective/tiles/advancedstatic/profiles/default/metadata.xml
src/collective/tiles/advancedstatic/profiles/default/registry.xml
src/collective/tiles/advancedstatic/profiles/mosaic_support/registry.xml
src/collective/tiles/advancedstatic/profiles/uninstall/browserlayer.xml
src/collective/tiles/advancedstatic/tests/__init__.py
src/collective/tiles/advancedstatic/tests/test_robot.py
src/collective/tiles/advancedstatic/tests/test_setup.py
src/collective/tiles/advancedstatic/tests/robot/test_example.robot