Metadata-Version: 1.1
Name: collective.tiles.advancedstatic
Version: 1.1.0
Summary: Advanced static tile for plone mosaic
Home-page: https://pypi.python.org/pypi/collective.tiles.advancedstatic
Author: Luca Bellenghi
Author-email: info@redturtle.it
License: GPL version 2
Keywords: Python Plone
Platform: UNKNOWN
Classifier: Environment :: Web Environment
Classifier: Framework :: Plone
Classifier: Framework :: Plone :: 5.0
Classifier: Framework :: Plone :: 5.1
Classifier: Framework :: Plone :: 5.2
Classifier: Programming Language :: Python
Classifier: Programming Language :: Python :: 2.7
Classifier: Programming Language :: Python :: 3.7
Classifier: Operating System :: OS Independent
Classifier: License :: OSI Approved :: GNU General Public License v2 (GPLv2)
